spectro_utils/__init__.py
spectro_utils/audio2spectro.py
spectro_utils/spectro2audio.py
spectro_utils-0.1.4.dist-info/METADATA
spectro_utils-0.1.4.dist-info/WHEEL
spectro_utils-0.1.4.dist-info/RECORD
